date62/__init__.py
date62/__main__.py
date62/__version__.py
date62/base62.py
date62/codec.py
date62/py.typed
date62/wrap.py
date62-0.2.0.dist-info/METADATA
date62-0.2.0.dist-info/WHEEL
date62-0.2.0.dist-info/entry_points.txt
date62-0.2.0.dist-info/licenses/LICENSE
date62-0.2.0.dist-info/RECORD
