Metadata-Version: 2.4
Name: date62
Version: 0.2.0
Summary: Compact string-based date(time) format for logging, data engineering, and visualizations.
Project-URL: Documentation, https://date62.readthedocs.io
Project-URL: Homepage, https://github.com/makukha/date62
Project-URL: Repository, https://github.com/makukha/date62
Project-URL: Issues, https://github.com/makukha/date62/issues
Project-URL: Changelog, https://github.com/makukha/date62/blob/main/CHANGELOG.md
Author-email: Michael Makukha <m.makukha@gmail.com>
License: MIT
License-File: LICENSE
Classifier: Development Status :: 4 - Beta
Classifier: Intended Audience :: Developers
Classifier: License :: OSI Approved :: MIT License
Classifier: Operating System :: OS Independent
Classifier: Programming Language :: Python
Classifier: Programming Language :: Python :: 2
Classifier: Programming Language :: Python :: 2.7
Classifier: Programming Language :: Python :: 3
Classifier: Programming Language :: Python :: 3.5
Classifier: Programming Language :: Python :: 3.6
Classifier: Programming Language :: Python :: 3.7
Classifier: Programming Language :: Python :: 3.8
Classifier: Programming Language :: Python :: 3.9
Classifier: Programming Language :: Python :: 3.10
Classifier: Programming Language :: Python :: 3.11
Classifier: Programming Language :: Python :: 3.12
Classifier: Programming Language :: Python :: 3.13
Classifier: Programming Language :: Python :: 3.14
Classifier: Topic :: Software Development
Classifier: Topic :: Software Development :: Libraries
Classifier: Typing :: Typed
Requires-Python: !=3.0,!=3.1,!=3.2,!=3.3,!=3.4,>=2.7
